setup.cfg
setup.py
quickgist/__init__.py
quickgist/quickgist.py
quickgist.egg-info/PKG-INFO
quickgist.egg-info/SOURCES.txt
quickgist.egg-info/dependency_links.txt
quickgist.egg-info/entry_points.txt
quickgist.egg-info/requires.txt
quickgist.egg-info/top_level.txt