Metadata-Version: 1.0
Name: quickgist
Version: 0.1.2
Summary: Command line tool for creating gists
Home-page: https://github.com/astocko/quickgist
Author: Alexander Stocko
Author-email: as@coder.gg
License: MIT
Keywords: gist,github
Platform: UNKNOWN
